setup.py
pbs_calculator/Calculator.py
pbs_calculator/__init__.py
pbs_calculator.egg-info/PKG-INFO
pbs_calculator.egg-info/SOURCES.txt
pbs_calculator.egg-info/dependency_links.txt
pbs_calculator.egg-info/not-zip-safe
pbs_calculator.egg-info/top_level.txt