Metadata-Version: 1.0
Name: pbs-calculator
Version: 0.1
Summary: Simple calculator
Home-page: UNKNOWN
Author: Prema S
Author-email: UNKNOWN
License: UNKNOWN
Platform: UNKNOWN
